Metadata-Version: 2.1
Name: symbolic-learn
Version: 0.1.4
Summary: A sklearn-compatible package that implements a symbolic regression model
Author-email: Vincent Papelard <papelardvincent@gmail.com>
Project-URL: Homepage, https://github.com/vinpap/symbolic-learn
Project-URL: Documentation, https://symbolic-learn.readthedocs.io/en/latest/
Classifier: Programming Language :: Python :: 3
Classifier: License :: OSI Approved :: MIT License
Classifier: Operating System :: OS Independent
Requires-Python: >=3.7
License-File: LICENSE.txt
Requires-Dist: Cython
Requires-Dist: joblib
Requires-Dist: numpy
Requires-Dist: pandas
Requires-Dist: scikit_learn
Requires-Dist: setuptools
Requires-Dist: sympy
